{"GPL19918": [{"GSM1638828": [{"title": "SK-N-AS + DMSO biol repl 01"}, {"type": "RNA"}, {"source_name_ch1": "Human neuroblastoma cell line SK-N-AS"}, {"characteristics_ch1": "cell line: SK-N-AS;\tcell type: neuroblastoma;\ttreatment: DMSO biol repl 01"}]}, {"GSM1638829": [{"title": "SK-N-AS + DMSO biol repl 02"}, {"type": "RNA"}, {"source_name_ch1": "Human neuroblastoma cell line SK-N-AS"}, {"characteristics_ch1": "cell line: SK-N-AS;\tcell type: neuroblastoma;\ttreatment: DMSO biol repl 02"}]}, {"GSM1638830": [{"title": "SK-N-AS + DMSO biol repl 03"}, {"type": "RNA"}, {"source_name_ch1": "Human neuroblastoma cell line SK-N-AS"}, {"characteristics_ch1": "cell line: SK-N-AS;\tcell type: neuroblastoma;\ttreatment: DMSO biol repl 03"}]}, {"GSM1638831": [{"title": "SK-N-AS + GSK461364 biol repl 01"}, {"type": "RNA"}, {"source_name_ch1": "Human neuroblastoma cell line SK-N-AS"}, {"characteristics_ch1": "cell line: SK-N-AS;\tcell type: neuroblastoma;\ttreatment: GSK461364 biol repl 01"}]}, {"GSM1638832": [{"title": "SK-N-AS + GSK461364 biol repl 02"}, {"type": "RNA"}, {"source_name_ch1": "Human neuroblastoma cell line SK-N-AS"}, {"characteristics_ch1": "cell line: SK-N-AS;\tcell type: neuroblastoma;\ttreatment: GSK461364 biol repl 02"}]}, {"GSM1638833": [{"title": "SK-N-AS + GSK461364 biol repl 03"}, {"type": "RNA"}, {"source_name_ch1": "Human neuroblastoma cell line SK-N-AS"}, {"characteristics_ch1": "cell line: SK-N-AS;\tcell type: neuroblastoma;\ttreatment: GSK461364 biol repl 03"}]}]}